[
  {
    "id": 6022,
    "channelUrl": "https://www.youtube.com/channel/UCnarYWXO4WoA3iyQfo4BqUA",
    "name": "C.L.C.C",
    "thumbnail": "https://yt3.googleusercontent.com/5wSAPwB__4FHc_NRHx6nMenK-1FA9x9UniPzbLu9BHhMsALNAxtJw6gM7ix0N24wJV0Vx5WRYv0=s176-c-k-c0x00ffffff-no-rj",
    "subscribe": "451",
    "score": "451",
    "videoTitle": "終於可以打機了&講講RG有咩買【Virtual Dog/Apex Legends】",
    "videoViewCount": "375",
    "videoThumbnail": "https://i.ytimg.com/vi/iywuRX3PNfs/hqdefault.jpg?sqp=-oaymwEcCNACELwBSFXyq4qpAw4IARUAAIhCGAFwAcABBg==&rs=AOn4CLBSZcwO8G0nqQaZyU0HcC8YDbrozQ",
    "videoUrl": "http://youtu.be/iywuRX3PNfs",
    "rank": 1,
    "rankVar": null
  }
]