[
  {
    "id": 1260,
    "channelUrl": "https://www.youtube.com/channel/UCK9V2B22uJYu3N7eR_BT9QA",
    "name": "尾丸波爾卡",
    "thumbnail": "https://yt3.ggpht.com/ytc/AMLnZu9aFFtICizDVLTskMbwkP6nDpcEviZRpVPWcXAjIg=s176-c-k-c0x00ffffff-no-rj",
    "subscribe": "121萬",
    "score": "79,947",
    "videoTitle": "【歌枠/KARAOKE】心が歌いたがっているんだ！！！！！【尾丸ポルカ/ホロライブ】",
    "videoViewCount": "7.99萬",
    "videoThumbnail": "https://i.ytimg.com/vi/vn4ZP685Rsw/hqdefault.jpg?sqp=-oaymwEcCNACELwBSFXyq4qpAw4IARUAAIhCGAFwAcABBg==&rs=AOn4CLBcMtNszI3qd9FGLbDGfxWe9Clvfw",
    "videoUrl": "http://youtu.be/vn4ZP685Rsw",
    "rank": 1,
    "rankVar": null
  }
]